harreman/__init__.py
harreman/data/._.DS_Store
harreman/data/CellChatDB/complex_input_CellChatDB_human.csv
harreman/data/CellChatDB/complex_input_CellChatDB_mouse.csv
harreman/data/CellChatDB/complex_input_CellChatDB_v2_human.csv
harreman/data/CellChatDB/complex_input_CellChatDB_v2_mouse.csv
harreman/data/CellChatDB/interaction_input_CellChatDB_human.csv
harreman/data/CellChatDB/interaction_input_CellChatDB_mouse.csv
harreman/data/CellChatDB/interaction_input_CellChatDB_v2_human.csv
harreman/data/CellChatDB/interaction_input_CellChatDB_v2_mouse.csv
harreman/data/HarremanDB/HarremanDB_human.csv
harreman/data/HarremanDB/HarremanDB_human_extracellular.csv
harreman/data/HarremanDB/HarremanDB_mouse.csv
harreman/data/HarremanDB/HarremanDB_mouse_extracellular.csv
harreman/data/HarremanDB/Heterodimer_info_human.csv
harreman/data/HarremanDB/Heterodimer_info_mouse.csv
harreman/data/metabolic_genes/human_metabolic_genes.csv
harreman/data/metabolic_genes/mouse_metabolic_genes.csv
harreman/datasets/__init__.py
harreman/datasets/datasets.py
harreman/hotspot/__init__.py
harreman/hotspot/local_autocorrelation.py
harreman/hotspot/local_correlation.py
harreman/hotspot/models.py
harreman/hotspot/modules.py
harreman/plots/__init__.py
harreman/plots/plots.py
harreman/preprocessing/__init__.py
harreman/preprocessing/anndata.py
harreman/preprocessing/database.py
harreman/tools/__init__.py
harreman/tools/api.py
harreman/tools/cell_communication.py
harreman/tools/knn.py
harreman/vision/VISION_accessor.py
harreman/vision/__init__.py
harreman/vision/diffexp.py
harreman/vision/signature.py
harreman/vision/vision.py
harreman-0.1.3.dist-info/METADATA
harreman-0.1.3.dist-info/WHEEL
harreman-0.1.3.dist-info/licenses/LICENSE
harreman-0.1.3.dist-info/RECORD
